sendfox/__init__.py
sendfox/api.py
sendfox/client.py
sendfox/endpoints/__init__.py
sendfox/endpoints/campaigns.py
sendfox/endpoints/contacts.py
sendfox/endpoints/lists.py
sendfox/endpoints/me.py
sendfox/endpoints/root.py
sendfox/endpoints/unsubscribe.py
python_sendfox_api-0.1.3.dist-info/LICENSE
python_sendfox_api-0.1.3.dist-info/METADATA
python_sendfox_api-0.1.3.dist-info/WHEEL
python_sendfox_api-0.1.3.dist-info/top_level.txt
python_sendfox_api-0.1.3.dist-info/RECORD
