Metadata-Version: 2.1
Name: python-sendfox-api
Version: 0.1.3
Summary: A straighforward python client for Sendfox API
Home-page: https://github.com/knyazz/python-sendfox-api
Author: Smirnov.EV
Author-email: knyazz@gmail.com
License: UNKNOWN
Keywords: sendfox,python sendfox api
Platform: UNKNOWN
Classifier: Programming Language :: Python
Classifier: License :: OSI Approved :: MIT License
Classifier: Operating System :: OS Independent
Classifier: Topic :: Software Development :: Libraries :: Python Modules
Classifier: Intended Audience :: Developers
Classifier: Development Status :: 4 - Beta
Requires-Python: >=3.6
License-File: LICENSE
Requires-Dist: requests (==2.26.0)
